microprobe/__init__.py
microprobe/exceptions.py
microprobe/microprobe.cfg
microprobe/property.py
microprobe/code/__init__.py
microprobe/code/address.py
microprobe/code/bbl.py
microprobe/code/benchmark.py
microprobe/code/cfg.py
microprobe/code/context.py
microprobe/code/ins.py
microprobe/code/var.py
microprobe/code/wrapper.py
microprobe/definitions/__init__.py
microprobe/definitions/generic/__init__.py
microprobe/definitions/generic/policies/__init__.py
microprobe/definitions/generic/policies/debug.py
microprobe/definitions/generic/templates/__init__.py
microprobe/definitions/generic/templates/c2mpt.c
microprobe/definitions/generic/templates/c2mpt.h
microprobe/definitions/generic/templates/c2mpt_template.c
microprobe/definitions/generic/tools/__init__.py
microprobe/definitions/generic/tools/mp_bin2asm.py
microprobe/definitions/generic/tools/mp_bin2objdump.py
microprobe/definitions/generic/tools/mp_c2mpt.py
microprobe/definitions/generic/tools/mp_epi.py
microprobe/definitions/generic/tools/mp_mpt2bin.py
microprobe/definitions/generic/tools/mp_mpt2elf.py
microprobe/definitions/generic/tools/mp_mpt2test.py
microprobe/definitions/generic/tools/mp_objdump2mpt.py
microprobe/definitions/generic/tools/mp_seq.py
microprobe/definitions/generic/tools/mp_seqtune.py
microprobe/definitions/generic/tools/mp_target.py
microprobe/definitions/generic/wrappers/__init__.py
microprobe/definitions/generic/wrappers/asm.py
microprobe/definitions/generic/wrappers/asmld.py
microprobe/definitions/generic/wrappers/bin.py
microprobe/definitions/generic/wrappers/c.py
microprobe/definitions/generic/wrappers/cpapi.py
microprobe/definitions/generic/wrappers/debug.py
microprobe/definitions/generic/wrappers/trace.py
microprobe/driver/__init__.py
microprobe/driver/genetic.py
microprobe/driver/guided.py
microprobe/model/__init__.py
microprobe/model/memory.py
microprobe/passes/__init__.py
microprobe/passes/address/__init__.py
microprobe/passes/branch/__init__.py
microprobe/passes/dat/__init__.py
microprobe_core-0.5.20250911152917.dist-info/licenses/LICENSE
microprobe_core-0.5.20250911152917.dist-info/METADATA
microprobe_core-0.5.20250911152917.dist-info/WHEEL
microprobe_core-0.5.20250911152917.dist-info/entry_points.txt
microprobe_core-0.5.20250911152917.dist-info/top_level.txt
microprobe_core-0.5.20250911152917.dist-info/RECORD
